README.md
setup.cfg
setup.py
email_analysis/__init__.py
email_analysis/email_analysis.py
email_analysis.egg-info/PKG-INFO
email_analysis.egg-info/SOURCES.txt
email_analysis.egg-info/dependency_links.txt
email_analysis.egg-info/not-zip-safe
email_analysis.egg-info/top_level.txt