Metadata-Version: 1.0
Name: email-analysis
Version: 0.0
Summary: Email analysis
Home-page: UNKNOWN
Author: UNKNOWN
Author-email: egor.kuzovkin.zr@gmail.com
License: UNKNOWN
Platform: UNKNOWN
